Workbook

Sheet Supuestos
A1: SUPUESTOS Y PARÁMETROS DEL MODELO
A2: .
A3: Parámetro | B3: Valor | C3: Unidad
A4: 1. Parámetros financieros
A5: TRM — Tasa Representativa del Mercado (USD → COP) | B5: 3250 | C5: COP/USD
A6: Horizonte de evaluación del proyecto | B6: 5 | C6: años
A7: Tasa de descuento nominal anual | B7: 0.15 | C7: % anual
A8: Inflación anual proyectada (COP) | B8: 0.045 | C8: % anual
A10: 2. Parámetros laborales — Colombia 2026
A11: Salario Mínimo Mensual Legal Vigente (SMMLV) 2026 | B11: 1750905 | C11: COP/mes
A12: Factor prestacional y de seguridad social a cargo del empleador | B12: 0.4 | C12: % s/salario
A13: Salario mensual — Ingeniero de Automatización | B13: 3500000 | C13: COP/mes
A14: Número de integrantes del equipo | B14: 6 | C14: personas
A15: Meses de dedicación al proyecto | B15: 5 | C15: meses
A16: % de dedicación promedio del equipo | B16: 0.7 | C16: %
A17: Salario mensual — Operario de producción/paletizado | B17: 1850000 | C17: COP/mes
A19: 3. Producción y OEE — Línea 1 (237 mL), Módulos 1-2 ya auditados
A20: Velocidad Línea 1 (237 mL) | B20: 38000 | C20: bot/h
A21: OEE actual | B21: 0.731 | C21: %
A22: OEE objetivo (planta automatizada a nivel MES) | B22: 0.846 | C22: %
A23: Capacidad de referencia (PC) | B23: 2128000 | C23: bot/semana
A25: 4. Escenario de automatización — mano de obra desplazada (beneficio cierto)
A26: Operarios de paletizado manual desplazados | B26: 2 | C26: personas/turno
A27: Turnos de operación por día | B27: 2 | C27: turnos/día
A28: ¿Incluir módulo opcional de clasificación robotizada (IRB 140 + visión)? | B28: No | C28: Sí / No
A29: Operarios de inspección manual desplazados (si se incluye el módulo) | B29: 2 | C29: personas/turno
A31: 5. Beneficio potencial por mejora de OEE
A32: % de la producción adicional efectivamente vendida (absorción comercial) | B32: 0.5 | C32: %
A33: Precio neto estimado por unidad personal 237 mL (embotellador, excl. margen de canal e IVA) | B33: 1600 | C33: COP/unidad
A34: Margen bruto de referencia | B34: 0.45 | C34: %
A36: 6. Operación y mantenimiento
A37: Mantenimiento anual (% del CAPEX en equipos) | B37: 0.04 | C37: % anual
A38: Repuestos y consumibles anual (% del CAPEX en equipos) | B38: 0.01 | C38: % anual
A39: Tarifa de energía eléctrica industrial | B39: 750 | C39: COP/kWh
A40: Potencia eléctrica adicional instalada (robot + PLC + HMI) | B40: 6 | C40: kW promedio
A41: Soporte anual de software Rockwell (TechConnect) | B41: 1800 | C41: USD/año

Sheet Nomina
A1: NÓMINA DEL EQUIPO DE INGENIERÍA — COSTO DEL PROYECTO
A2: Costo ÚNICO de ejecución (CAPEX de mano de obra), no es nómina recurrente de planta.
A3: Integrante | B3: Rol | C3: Salario mensual (COP) | D3: Factor prestacional | E3: Meses dedicación | F3: % dedicación | G3: Costo total proyecto (COP)
A4: Nicolas Fernando Davila Peñuela | B4: Ingeniero de Automatización | C4: =Supuestos!$B$13 -> 3500000 | D4: =Supuestos!$B$12 -> 0.4 | E4: =Supuestos!$B$15 -> 5 | F4: =Supuestos!$B$16 -> 0.7 | G4: =C4*(1+D4)*E4*F4 -> 17150000
A5: Juan David Meza Criollo | B5: Ingeniero de Automatización | C5: =Supuestos!$B$13 -> 3500000 | D5: =Supuestos!$B$12 -> 0.4 | E5: =Supuestos!$B$15 -> 5 | F5: =Supuestos!$B$16 -> 0.7 | G5: =C5*(1+D5)*E5*F5 -> 17150000
A6: Cristian Fabián Martínez Bohorquez | B6: Ingeniero de Automatización | C6: =Supuestos!$B$13 -> 3500000 | D6: =Supuestos!$B$12 -> 0.4 | E6: =Supuestos!$B$15 -> 5 | F6: =Supuestos!$B$16 -> 0.7 | G6: =C6*(1+D6)*E6*F6 -> 17150000
A7: Andres Mauricio Avilan Herrera | B7: Ingeniero de Automatización | C7: =Supuestos!$B$13 -> 3500000 | D7: =Supuestos!$B$12 -> 0.4 | E7: =Supuestos!$B$15 -> 5 | F7: =Supuestos!$B$16 -> 0.7 | G7: =C7*(1+D7)*E7*F7 -> 17150000
A8: Santiago Avila Corredor | B8: Ingeniero de Automatización | C8: =Supuestos!$B$13 -> 3500000 | D8: =Supuestos!$B$12 -> 0.4 | E8: =Supuestos!$B$15 -> 5 | F8: =Supuestos!$B$16 -> 0.7 | G8: =C8*(1+D8)*E8*F8 -> 17150000
A9: Juan José Delgado Estrada | B9: Ingeniero de Automatización | C9: =Supuestos!$B$13 -> 3500000 | D9: =Supuestos!$B$12 -> 0.4 | E9: =Supuestos!$B$15 -> 5 | F9: =Supuestos!$B$16 -> 0.7 | G9: =C9*(1+D9)*E9*F9 -> 17150000
A10: TOTAL NÓMINA DEL PROYECTO (6 integrantes) | G10: =SUM(G4:G9) -> 102900000
A12: Nota: se asignó el mismo salario y dedicación a los 6 integrantes por simplicidad. Si un rol difiere (p. ej. líder de proyecto), sobrescriba manualmente la celda de esa fila en la columna "Salario mensual".

Sheet CAPEX
A1: CAPEX — INVERSIÓN INICIAL DEL PROYECTO
A4: Ítem | B4: Categoría | C4: Cantidad | D4: Precio unit. (USD) | E4: Precio unit. (COP) | F4: Subtotal (COP)
A5: Robot paletizador ABB IRB 660 (IRC5, 250 kg, 3,15 m) | B5: Equipo | C5: 1 | D5: 35000 | E5: =D5*Supuestos!$B$5 -> 113750000 | F5: =C5*E5 -> 113750000
A6: Sistema de control PLC Allen-Bradley ControlLogix 5570 (1756-L7x + chasis + fuente + módulos E/S) | B6: Equipo | C6: 1 | D6: 11000 | E6: =D6*Supuestos!$B$5 -> 35750000 | F6: =C6*E6 -> 35750000
A7: HMI Allen-Bradley PanelView Plus 7, pantalla 7" (2711P-T7C22D9P) | B7: Equipo | C7: 1 | D7: 2200 | E7: =D7*Supuestos!$B$5 -> 7150000 | F7: =C7*E7 -> 7150000
A8: Software Rockwell: Studio 5000 Professional (licencia perpetua) + RSLinx Classic / FactoryTalk Linx | B8: Software | C8: 1 | D8: 8500 | E8: =D8*Supuestos!$B$5 -> 27625000 | F8: =C8*E8 -> 27625000
A9: Licencia Siemens NX CAD / NX X Design (1 usuario/año) | B9: Software | C9: 1 | D9: 9480 | E9: =D9*Supuestos!$B$5 -> 30810000 | F9: =C9*E9 -> 30810000
A10: Materiales de integración mecánica y cableado | B10: Material | C10: 1 | E10: 15000000 | F10: =C10*E10 -> 15000000
A11: Seguridad industrial: cerramiento perimetral, cortina de luz, paros de emergencia, relés de seguridad | B11: Material | C11: 1 | E11: 18000000 | F11: =C11*E11 -> 18000000
A12: Montaje, pruebas y puesta en marcha (contratista especializado) | B12: Servicio | C12: 1 | E12: 20000000 | F12: =C12*E12 -> 20000000
A15: Subtotal equipos, software y materiales | F15: =SUM(F5:F12) -> 268085000
A16: Nómina del equipo de ingeniería (costo único del proyecto — ver hoja Nomina) | F16: =Nomina!$G$10 -> 102900000
A17: Subtotal directo | F17: =F15+F16 -> 370985000
A18: Imprevistos e indirectos | E18: 0.15 | F18: =F17*E18 -> 55647750
A19: TOTAL CAPEX | F19: =F17+F18 -> 426632750

Sheet OPEX
A1: OPEX — COSTOS OPERATIVOS ANUALES
A4: Concepto | B4: Base de cálculo | C4: Valor anual (COP)
A5: Mantenimiento preventivo/correctivo | B5: % del CAPEX en equipos | C5: =CAPEX!$F$15*Supuestos!$B$37 -> 10723400
A6: Repuestos y consumibles | B6: % del CAPEX en equipos | C6: =CAPEX!$F$15*Supuestos!$B$38 -> 2680850
A7: Soporte anual de software | B7: USD/año × TRM | C7: =Supuestos!$B$41*Supuestos!$B$5 -> 5850000
A8: Energía eléctrica adicional | B8: kW instalados × horas de operación anuales × tarifa | C8: =Supuestos!$B$40*(Supuestos!$B$23/Supuestos!$B$20*52)*Supuestos!$B$39 -> 13104000
A10: TOTAL OPEX ANUAL | C10: =SUM(C5:C8) -> 32358250

Sheet Beneficios
A1: BENEFICIOS DEL PROYECTO
A4: A. Beneficios ciertos
A5: Concepto | B5: Cálculo | C5: Valor anual (COP)
A6: Ahorro de mano de obra — paletizado manual reemplazado por el robot ABB IRB 660 | B6: Operarios/turno × turnos/día × salario × (1+factor prestacional) × 12 meses | C6: =Supuestos!$B$26*Supuestos!$B$27*Supuestos!$B$17*(1+Supuestos!$B$12)*12 -> 124320000
A7: Ahorro de mano de obra — inspección/clasificación manual (solo si el módulo opcional IRB140+visión se incluye) | B7: Igual al anterior, con operarios de inspección; 0 si el módulo no se incluye | C7: =IF(Supuestos!$B$28="Sí", Supuestos!$B$29*Supuestos!$B$27*Supuestos!$B$17*(1+Supuestos!$B$12)*12, 0) -> 0
A9: TOTAL BENEFICIOS CIERTOS ANUALES | C9: =SUM(C6:C7) -> 124320000
A11: B. Beneficio potencial por mejora de OEE
A12: Concepto | B12: Cálculo | C12: Valor
A13: Botellas adicionales por año (cierre de la brecha de OEE) | B13: PC semanal × (OEE objetivo − OEE actual) × 52 semanas | C13: =Supuestos!$B$23*(Supuestos!$B$22-Supuestos!$B$21)*52 -> 12725440
A14: Botellas monetizables (según % de absorción comercial) | B14: Fila anterior × % de absorción comercial (Supuestos) | C14: =C13*Supuestos!$B$32 -> 6362720
A15: Beneficio unitario estimado (precio neto × margen bruto) | B15: Precio neto por botella × margen bruto de referencia (Supuestos) | C15: =Supuestos!$B$33*Supuestos!$B$34 -> 720
A17: BENEFICIO POTENCIAL ANUAL POR OEE | C17: =C14*C15 -> 4.5811584e+09

Sheet FlujoCaja
A1: FLUJO DE CAJA Y RENTABILIDAD (10 años; el horizonte real lo define Supuestos)
A3: Año | B3: 0 | C3: 1 | D3: 2 | E3: 3 | F3: 4 | G3: 5 | H3: 6 | I3: 7 | J3: 8 | K3: 9 | L3: 10
A5: Inversión (CAPEX) | B5: =-CAPEX!$F$19 -> -426632750 | C5: 0 | D5: 0 | E5: 0 | F5: 0 | G5: 0 | H5: 0 | I5: 0 | J5: 0 | K5: 0 | L5: 0
A6: Beneficios ciertos | B6: 0 | C6: =IF(C$3<=Supuestos!$B$6,Beneficios!$C$9,0) -> 124320000 | D6: =IF(D$3<=Supuestos!$B$6,Beneficios!$C$9,0) -> 124320000 | E6: =IF(E$3<=Supuestos!$B$6,Beneficios!$C$9,0) -> 124320000 | F6: =IF(F$3<=Supuestos!$B$6,Beneficios!$C$9,0) -> 124320000 | G6: =IF(G$3<=Supuestos!$B$6,Beneficios!$C$9,0) -> 124320000 | H6: =IF(H$3<=Supuestos!$B$6,Beneficios!$C$9,0) -> 0 | I6: =IF(I$3<=Supuestos!$B$6,Beneficios!$C$9,0) -> 0 | J6: =IF(J$3<=Supuestos!$B$6,Beneficios!$C$9,0) -> 0 | ... L6: =IF(L$3<=Supuestos!$B$6,Beneficios!$C$9,0) -> 0
A7: OPEX | B7: 0 | C7: =IF(C$3<=Supuestos!$B$6,-OPEX!$C$10,0) -> -32358250 | D7: =IF(D$3<=Supuestos!$B$6,-OPEX!$C$10,0) -> -32358250 | E7: =IF(E$3<=Supuestos!$B$6,-OPEX!$C$10,0) -> -32358250 | F7: =IF(F$3<=Supuestos!$B$6,-OPEX!$C$10,0) -> -32358250 | G7: =IF(G$3<=Supuestos!$B$6,-OPEX!$C$10,0) -> -32358250 | H7: =IF(H$3<=Supuestos!$B$6,-OPEX!$C$10,0) -> 0 | I7: =IF(I$3<=Supuestos!$B$6,-OPEX!$C$10,0) -> 0 | J7: =IF(J$3<=Supuestos!$B$6,-OPEX!$C$10,0) -> 0 | ... L7: =IF(L$3<=Supuestos!$B$6,-OPEX!$C$10,0) -> 0
A8: Flujo neto | B8: =SUM(B5:B7) -> -426632750 | C8: =SUM(C5:C7) -> 91961750 | D8: =SUM(D5:D7) -> 91961750 | E8: =SUM(E5:E7) -> 91961750 | F8: =SUM(F5:F7) -> 91961750 | G8: =SUM(G5:G7) -> 91961750 | H8: =SUM(H5:H7) -> 0 | I8: =SUM(I5:I7) -> 0 | ... L8: =SUM(L5:L7) -> 0
A9: Flujo acumulado | B9: =B8 -> -426632750 | C9: =B9+C8 -> -334671000 | D9: =C9+D8 -> -242709250 | E9: =D9+E8 -> -150747500 | F9: =E9+F8 -> -58785750 | G9: =F9+G8 -> 33176000 | H9: =G9+H8 -> 33176000 | I9: =H9+I8 -> 33176000 | J9: =I9+J8 -> 33176000 | ... L9: =K9+L8 -> 33176000
A10: Factor de descuento | B10: =1/(1+Supuestos!$B$7)^B$3 -> 1 | C10: =1/(1+Supuestos!$B$7)^C$3 -> 0.86956522 | D10: =1/(1+Supuestos!$B$7)^D$3 -> 0.75614367 | E10: =1/(1+Supuestos!$B$7)^E$3 -> 0.65751623 | F10: =1/(1+Supuestos!$B$7)^F$3 -> 0.57175325 | G10: =1/(1+Supuestos!$B$7)^G$3 -> 0.49717674 | H10: =1/(1+Supuestos!$B$7)^H$3 -> 0.4323276 | I10: =1/(1+Supuestos!$B$7)^I$3 -> 0.37593704 | ... L10: =1/(1+Supuestos!$B$7)^L$3 -> 0.24718471
A11: Flujo descontado | B11: =B8*B10 -> -426632750 | C11: =C8*C10 -> 79966739 | D11: =D8*D10 -> 69536295 | E11: =E8*E10 -> 60466343 | F11: =F8*F10 -> 52579429 | G11: =G8*G10 -> 45721243 | H11: =H8*H10 -> 0 | I11: =I8*I10 -> 0 | ... L11: =L8*L10 -> 0
A13: Acumulado ≥ 0 | B13: =IF(B9>=0,1,0) -> 0 | C13: =IF(C9>=0,1,0) -> 0 | D13: =IF(D9>=0,1,0) -> 0 | E13: =IF(E9>=0,1,0) -> 0 | F13: =IF(F9>=0,1,0) -> 0 | G13: =IF(G9>=0,1,0) -> 1 | H13: =IF(H9>=0,1,0) -> 1 | I13: =IF(I9>=0,1,0) -> 1 | ... L13: =IF(L9>=0,1,0) -> 1
A15: VAN — Valor Presente Neto | C15: =SUM(B11:L11) -> -1.183627e+08
A16: TIR — Tasa Interna de Retorno | C16: =IFERROR(IRR(B8:L8),"n/a") -> 0.025493093
A18: Año de recuperación entero | C18: =MATCH(1,B13:L13,0)-1 -> 5
A19: Acumulado en el año anterior al de recuperación | C19: =INDEX(B9:L9,1,C18) -> -58785750
A20: [Flujo neto del año de recuperación | C20: =INDEX(B8:L8,1,C18+1) -> 91961750
A22: Payback simple (años) | C22: =IFERROR((C18-1)+(-C19/C20),"n/a") -> 4.6392413
A23: ROI al horizonte de evaluación | C23: =IFERROR(INDEX(B9:L9,1,Supuestos!$B$6+1)/CAPEX!$F$19,"n/a") -> 0.077762432
A24: ROI anualizado equivalente (CAGR) | C24: =IFERROR((1+C23)^(1/Supuestos!$B$6)-1,"n/a") -> 0.015090137

Sheet Resumen
A1: RESUMEN EJECUTIVO — EVALUACIÓN ECONÓMICA DEL PROYECTO
A2: Chibcho Sistemas · Automatización
A4: Indicadores clave
A5: Indicador | B5: Valor | C5: Nota
A6: CAPEX total (inversión inicial) | B6: =CAPEX!$F$19 -> 426632750 | C6: Equipos, software, materiales, seguridad, montaje y nómina del proyecto.
A7: OPEX anual | B7: =OPEX!$C$10 -> 32358250 | C7: Mantenimiento, energía, repuestos y soporte de software.
A8: Beneficios ciertos anuales | B8: =Beneficios!$C$9 -> 124320000 | C8: Ahorro de mano de obra por paletizado.
A9: Flujo neto anual (beneficios − OPEX) | B9: =B8-B7 -> 91961750
A10: Payback simple | B10: =FlujoCaja!$C$22 -> 4.6392413 | C10: Años para recuperar el CAPEX con el flujo neto nominal.
A11: VAN (@ tasa de descuento de Supuestos) | B11: =FlujoCaja!$C$15 -> -1.183627e+08 | C11: Valor presente neto a la tasa de descuento definida en Supuestos.
A12: TIR (Tasa Interna de Retorno) | B12: =FlujoCaja!$C$16 -> 0.025493093
A13: ROI al horizonte de evaluación | B13: =FlujoCaja!$C$23 -> 0.077762432 | C13: Ganancia neta acumulada sobre el CAPEX, al cabo del horizonte definido en Supuestos.
A14: ROI anualizado equivalente (CAGR) | B14: =FlujoCaja!$C$24 -> 0.015090137 | C14: El ROI anterior expresado como tasa de retorno anual equivalente.
A16: Beneficio potencial adicional
A17: Beneficio potencial anual por mejora de OEE | B17: =Beneficios!$C$17 -> 4.5811584e+09 | C17: Solo si el mercado absorbe la producción adicional liberada por el aumento de OEE.
